divided_by_odd/by5/divider_by5.v
`timescale 1ns / 1ps
//////////////////////////////////////////////////////////////////////////////////
// Company: 
// Engineer: 
// 
// Create Date: 05/20/2026 06:24:52 PM
// Design Name: 
// Module Name: divider_by5
// Project Name: 
// Target Devices: 
// Tool Versions: 
// Description: 
// 
// Dependencies: 
// 
// Revision:
// Revision 0.01 - File Created
// Additional Comments:
// 
//////////////////////////////////////////////////////////////////////////////////


module divider_by5(
input clk, reset,
output out
    );
    
    reg [2: 0] count;
    assign out = count[2];
    
    always @(posedge clk)
    if(reset == 1'b1) count <= 0;
    else  if(count == 4) count <= 0;
          else count <= count + 1;
          
endmodule

testbench.v
`timescale 1ns / 1ps
//////////////////////////////////////////////////////////////////////////////////
// Company: 
// Engineer: 
// 
// Create Date: 05/20/2026 08:20:45 PM
// Design Name: 
// Module Name: testbench
// Project Name: 
// Target Devices: 
// Tool Versions: 
// Description: 
// 
// Dependencies: 
// 
// Revision:
// Revision 0.01 - File Created
// Additional Comments:
// 
//////////////////////////////////////////////////////////////////////////////////


module testbench;

reg clk, reset;
wire out;

// Instantiate the Unit Under Test (UUT)
divider_by5 uut(
    .clk(clk), 
    .reset(reset),
    .out(out)
);
   
// Clock generation
initial clk = 0;
always #2 clk = ~clk;
 
initial begin
    $dumpfile("divider_by5.vcd"); 
    $dumpvars(0, testbench);

    $monitor("Time: %0t | Reset: %b | Output: %b", $time, reset, out);

    // reset logic
    reset = 1'b1;
    #3 reset = 1'b0;

    $display("Testbench completed successfully.");
    #100 $finish;
end 
   
endmodule

divider_by5.vcd
$date
	Thu Jun 11 00:53:37 2026
$end
$version
	Icarus Verilog
$end
$timescale
	1ps
$end
$scope module testbench $end
$var wire 1 ! out $end
$var reg 1 " clk $end
$var reg 1 # reset $end
$scope module uut $end
$var wire 1 " clk $end
$var wire 1 # reset $end
$var wire 1 ! out $end
$var reg 3 $ count [2:0] $end
$upscope $end
$upscope $end
$enddefinitions $end
$comment Show the parameter values. $end
$dumpall
$end
#0
$dumpvars
bx $
1#
0"
x!
$end
#2000
0!
b0 $
1"
#3000
0#
#4000
0"
#6000
b1 $
1"
#8000
0"
#10000
b10 $
1"
#12000
0"
#14000
b11 $
1"
#16000
0"
#18000
1!
b100 $
1"
#20000
0"
#22000
0!
b0 $
1"
#24000
0"
#26000
b1 $
1"
#28000
0"
#30000
b10 $
1"
#32000
0"
#34000
b11 $
1"
#36000
0"
#38000
1!
b100 $
1"
#40000
0"
#42000
0!
b0 $
1"
#44000
0"
#46000
b1 $
1"
#48000
0"
#50000
b10 $
1"
#52000
0"
#54000
b11 $
1"
#56000
0"
#58000
1!
b100 $
1"
#60000
0"
#62000
0!
b0 $
1"
#64000
0"
#66000
b1 $
1"
#68000
0"
#70000
b10 $
1"
#72000
0"
#74000
b11 $
1"
#76000
0"
#78000
1!
b100 $
1"
#80000
0"
#82000
0!
b0 $
1"
#84000
0"
#86000
b1 $
1"
#88000
0"
#90000
b10 $
1"
#92000
0"
#94000
b11 $
1"
#96000
0"
#98000
1!
b100 $
1"
#100000
0"
#102000
0!
b0 $
1"
